odoo/addons/l10n_es_sigaus_account/README.rst
odoo/addons/l10n_es_sigaus_account/__init__.py
odoo/addons/l10n_es_sigaus_account/__manifest__.py
odoo/addons/l10n_es_sigaus_account/hooks.py
odoo/addons/l10n_es_sigaus_account/data/data.xml
odoo/addons/l10n_es_sigaus_account/data/exception_templates.xml
odoo/addons/l10n_es_sigaus_account/i18n/ca.po
odoo/addons/l10n_es_sigaus_account/i18n/es.po
odoo/addons/l10n_es_sigaus_account/i18n/l10n_es_sigaus_account.pot
odoo/addons/l10n_es_sigaus_account/models/__init__.py
odoo/addons/l10n_es_sigaus_account/models/account_fiscal_position.py
odoo/addons/l10n_es_sigaus_account/models/account_move.py
odoo/addons/l10n_es_sigaus_account/models/account_move_line.py
odoo/addons/l10n_es_sigaus_account/models/l10n_es_sigaus_amount.py
odoo/addons/l10n_es_sigaus_account/models/product_category.py
odoo/addons/l10n_es_sigaus_account/models/product_product.py
odoo/addons/l10n_es_sigaus_account/models/product_template.py
odoo/addons/l10n_es_sigaus_account/models/res_company.py
odoo/addons/l10n_es_sigaus_account/models/res_partner.py
odoo/addons/l10n_es_sigaus_account/models/sigaus_line_mixin.py
odoo/addons/l10n_es_sigaus_account/models/sigaus_mixin.py
odoo/addons/l10n_es_sigaus_account/readme/CONFIGURE.rst
odoo/addons/l10n_es_sigaus_account/readme/CONTRIBUTORS.rst
odoo/addons/l10n_es_sigaus_account/readme/DESCRIPTION.rst
odoo/addons/l10n_es_sigaus_account/readme/ROADMAP.rst
odoo/addons/l10n_es_sigaus_account/readme/USAGE.rst
odoo/addons/l10n_es_sigaus_account/security/ir.model.access.csv
odoo/addons/l10n_es_sigaus_account/static/description/icon.png
odoo/addons/l10n_es_sigaus_account/static/description/icon.svg
odoo/addons/l10n_es_sigaus_account/static/description/index.html
odoo/addons/l10n_es_sigaus_account/tests/__init__.py
odoo/addons/l10n_es_sigaus_account/tests/common.py
odoo/addons/l10n_es_sigaus_account/tests/test_l10n_es_sigaus_account.py
odoo/addons/l10n_es_sigaus_account/tests/test_l10n_es_sigaus_general_values.py
odoo_addon_l10n_es_sigaus_account-16.0.1.0.3.3.dist-info/METADATA
odoo_addon_l10n_es_sigaus_account-16.0.1.0.3.3.dist-info/WHEEL
odoo_addon_l10n_es_sigaus_account-16.0.1.0.3.3.dist-info/top_level.txt
odoo_addon_l10n_es_sigaus_account-16.0.1.0.3.3.dist-info/RECORD
